memoryfields/EMFApiHelper.py
memoryfields/__init__.py
memoryfields-0.1.1.dist-info/METADATA
memoryfields-0.1.1.dist-info/WHEEL
memoryfields-0.1.1.dist-info/top_level.txt
memoryfields-0.1.1.dist-info/RECORD
