Metadata-Version: 2.2
Name: memoryfields
Version: 0.1.1
Summary: A Python client for interacting with SenTech AI's memory fields API.
Author-email: Sentech AI <service@sentech.ai>
License: MIT
Project-URL: Homepage, https://github.com/SentechAI/memory-fields
Project-URL: Repository, https://github.com/SentechAI/memory-fields
Requires-Python: >=3.7
Requires-Dist: requests
Requires-Dist: requests_toolbelt
